mailtools/__init__.py
mailtools/mailer.py
mailtools/threadedmailer.py
mailtools/utils.py
mailtools-3.0.1.dist-info/DESCRIPTION.rst
mailtools-3.0.1.dist-info/METADATA
mailtools-3.0.1.dist-info/RECORD
mailtools-3.0.1.dist-info/WHEEL
mailtools-3.0.1.dist-info/metadata.json
mailtools-3.0.1.dist-info/top_level.txt
