Metadata-Version: 2.0
Name: mailtools
Version: 3.0.1
Summary: Tools for constructing and sending emails
Home-page: https://hg.sr.ht/~olly/mailtools
Author: Oliver Cope
Author-email: oliver@redgecko.org
License: BSD
Platform: UNKNOWN
Classifier: Development Status :: 7 - Inactive
Classifier: Topic :: Communications :: Email
Classifier: Environment :: Web Environment
Classifier: License :: OSI Approved :: BSD License
Classifier: Programming Language :: Python
Classifier: Programming Language :: Python :: 3
Classifier: Programming Language :: Python :: 3 :: Only
